shellsec/__init__.py
shellsec/core.py
shellsec-1.0.1.dist-info/LICENSE
shellsec-1.0.1.dist-info/METADATA
shellsec-1.0.1.dist-info/WHEEL
shellsec-1.0.1.dist-info/entry_points.txt
shellsec-1.0.1.dist-info/top_level.txt
shellsec-1.0.1.dist-info/RECORD
