Metadata-Version: 2.1
Name: shellsec
Version: 1.0.1
Summary: A tool to encrypt and decrypt Bash scripts using Base64 encoding.
Home-page: https://github.com/ByteBreach/shellsec
Author: Fidal
Author-email: mrfidal@proton.me
Classifier: Programming Language :: Python :: 3
Classifier: License :: OSI Approved :: MIT License
Classifier: Operating System :: OS Independent
Requires-Python: >=3.6
License-File: LICENSE
